sphinx_material/__init__.py
sphinx_material/_version.py
sphinx_material/sphinx_material/comments.html
sphinx_material/sphinx_material/globaltoc.html
sphinx_material/sphinx_material/google_analytics.html
sphinx_material/sphinx_material/header.html
sphinx_material/sphinx_material/hero.html
sphinx_material/sphinx_material/layout.html
sphinx_material/sphinx_material/localtoc.html
sphinx_material/sphinx_material/logo-text.html
sphinx_material/sphinx_material/page.html
sphinx_material/sphinx_material/relbar.html
sphinx_material/sphinx_material/repo.html
sphinx_material/sphinx_material/search.html
sphinx_material/sphinx_material/searchbox.html
sphinx_material/sphinx_material/sidebar.html
sphinx_material/sphinx_material/sourcelink.html
sphinx_material/sphinx_material/theme.conf
sphinx_material/sphinx_material/version_dropdown.html
sphinx_material/sphinx_material/static/jquery.js
sphinx_material/sphinx_material/static/jquery.min.map
sphinx_material/sphinx_material/static/material.css_t
sphinx_material/sphinx_material/static/fonts/font-awesome.css
sphinx_material/sphinx_material/static/fonts/material-icons.css
sphinx_material/sphinx_material/static/fonts/specimen/FontAwesome.ttf
sphinx_material/sphinx_material/static/fonts/specimen/FontAwesome.woff
sphinx_material/sphinx_material/static/fonts/specimen/FontAwesome.woff2
sphinx_material/sphinx_material/static/fonts/specimen/MaterialIcons-Regular.ttf
sphinx_material/sphinx_material/static/fonts/specimen/MaterialIcons-Regular.woff
sphinx_material/sphinx_material/static/fonts/specimen/MaterialIcons-Regular.woff2
sphinx_material/sphinx_material/static/images/favicon.png
sphinx_material/sphinx_material/static/images/icons/bitbucket.1b09e088.svg
sphinx_material/sphinx_material/static/images/icons/bitbucket.svg
sphinx_material/sphinx_material/static/images/icons/github.f0b8504a.svg
sphinx_material/sphinx_material/static/images/icons/github.svg
sphinx_material/sphinx_material/static/images/icons/gitlab.6dd19c00.svg
sphinx_material-0.0.36.dist-info/LICENSE.md
sphinx_material-0.0.36.dist-info/METADATA
sphinx_material-0.0.36.dist-info/WHEEL
sphinx_material-0.0.36.dist-info/entry_points.txt
sphinx_material-0.0.36.dist-info/top_level.txt
sphinx_material-0.0.36.dist-info/RECORD
