Metadata-Version: 2.1
Name: sphinx-material
Version: 0.0.36
Summary: Material sphinx theme
Home-page: https://github.com/bashtage/sphinx-material
Author: Kevin Sheppard
Author-email: kevin.k.sheppard@gmail.com
License: MIT
Classifier: Development Status :: 3 - Alpha
Classifier: Intended Audience :: Developers
Classifier: Natural Language :: English
Classifier: License :: OSI Approved :: MIT License
Classifier: Programming Language :: Python
Classifier: Framework :: Sphinx :: Extension
Classifier: Framework :: Sphinx :: Theme
Classifier: Topic :: Documentation :: Sphinx
Classifier: Programming Language :: Python :: 3.6
Classifier: Programming Language :: Python :: 3.7
Requires-Python: >=3.6
Provides-Extra: dev
License-File: LICENSE.md
